joinery/__init__.py
joinery-0.0.1.dist-info/LICENSE
joinery-0.0.1.dist-info/METADATA
joinery-0.0.1.dist-info/WHEEL
joinery-0.0.1.dist-info/top_level.txt
joinery-0.0.1.dist-info/RECORD
