Metadata-Version: 2.1
Name: joinery
Version: 0.0.1
Summary: Tools for joining data on the application side.
Author-email: dennisvang <djvg@protonmail.com>
License: MIT License
Project-URL: source, https://github.com/dennisvang/django-joinery
Project-URL: documentation, https://github.com/dennisvang/django-joinery
Project-URL: issues, https://github.com/dennisvang/django-joinery/issues
Classifier: Programming Language :: Python :: 3
Classifier: License :: OSI Approved :: MIT License
Classifier: Operating System :: OS Independent
Requires-Python: >=3.8
License-File: LICENSE
Requires-Dist: django >=3.2.21
